cleanprompt/__init__.py
cleanprompt/about.py
cleanprompt/prompt.py
cleanprompt/py.typed
cleanprompt-0.1.1.dist-info/METADATA
cleanprompt-0.1.1.dist-info/WHEEL
cleanprompt-0.1.1.dist-info/licenses/LICENSE
cleanprompt-0.1.1.dist-info/RECORD
