Metadata-Version: 2.4
Name: cleanprompt
Version: 0.1.1
Summary: Utility to correctly strip LLM prompts
Project-URL: Homepage, https://github.com/salarian/cleanprompt
Project-URL: Bug Tracker, https://github.com/salarian/cleanprompt/issues
Author-email: Arash Salarian <arash@salarian.com>
License-Expression: MIT
License-File: LICENSE
Classifier: Intended Audience :: Developers
Classifier: Operating System :: OS Independent
Classifier: Programming Language :: Python :: 3 :: Only
Classifier: Programming Language :: Python :: 3.12
Classifier: Programming Language :: Python :: 3.13
Classifier: Programming Language :: Python :: 3.14
Requires-Python: <3.15,>=3.12.0
Provides-Extra: dev
Requires-Dist: hatch>=1.14; extra == 'dev'
Requires-Dist: mypy~=1.18.2; extra == 'dev'
Requires-Dist: pre-commit~=v4.3.0; extra == 'dev'
Requires-Dist: pytest-cov>=6.0; extra == 'dev'
Requires-Dist: pytest>=8.3; extra == 'dev'
Requires-Dist: ruff~=0.14.0; extra == 'dev'
